future_sales_inno_ds_project/__init__.py
future_sales_inno_ds_project/config.py
future_sales_inno_ds_project/data_preparation/__init__.py
future_sales_inno_ds_project/data_preparation/data_loader.py
future_sales_inno_ds_project/data_preparation/data_preprocessor.py
future_sales_inno_ds_project/data_preparation/standard_scaler_handler.py
future_sales_inno_ds_project/feature_engineering/__init__.py
future_sales_inno_ds_project/feature_engineering/feature_engineer.py
future_sales_inno_ds_project/feature_engineering/feature_importance_evaluator.py
future_sales_inno_ds_project/feature_engineering/feature_selector.py
future_sales_inno_ds_project/model_interpetation/__init__.py
future_sales_inno_ds_project/model_interpetation/model_interpreter.py
future_sales_inno_ds_project/model_trainer.py
future_sales_inno_ds_project/modeling/__init__.py
future_sales_inno_ds_project/modeling/hyperopt_tuner.py
future_sales_inno_ds_project/modeling/model_factory.py
future_sales_inno_ds_project/modeling/optuna_tuner.py
future_sales_inno_ds_project/modeling/validator.py
future_sales_inno_ds_project/pipeline.py
future_sales_inno_ds_project/utills/__init__.py
future_sales_inno_ds_project/utills/logger.py
future_sales_inno_ds_project-0.0.18.dist-info/METADATA
future_sales_inno_ds_project-0.0.18.dist-info/WHEEL
future_sales_inno_ds_project-0.0.18.dist-info/entry_points.txt
future_sales_inno_ds_project-0.0.18.dist-info/RECORD
