Metadata-Version: 2.4
Name: future_sales_inno_ds_project
Version: 0.0.18
Summary: DS project
Author: Katsiaryna
Author-email: katsiaryna.shymchonak@innowise.com
Requires-Python: >=3.11,<3.12
Classifier: Programming Language :: Python :: 3
Classifier: Programming Language :: Python :: 3.11
Requires-Dist: PyGithub (>=2.4.0,<2.5.0)
Requires-Dist: charset-normalizer (>=3.3.0)
Requires-Dist: dill (>=0.3.8,<0.4.0)
Requires-Dist: hyperopt (>=0.2.7,<0.3.0)
Requires-Dist: keras (>=2.14.0,<2.15.0)
Requires-Dist: lightgbm (>=4.6.0,<4.7.0)
Requires-Dist: matplotlib (>=3.8.0)
Requires-Dist: neptune (>=1.14.0,<1.15.0)
Requires-Dist: numpy (>=1.26.0,<1.27.0)
Requires-Dist: openai (>=2.2.0,<2.3.0)
Requires-Dist: optuna (>=4.5.0,<4.6.0)
Requires-Dist: pandas (>=2.1.1,<2.2.0)
Requires-Dist: protobuf (>=4.23.4,<4.24.0)
Requires-Dist: python-dotenv (>=0.21.1,<0.22.0)
Requires-Dist: requests (>=2.32.4,<2.33.0)
Requires-Dist: scikit-learn (>=1.3.2,<1.4.0)
Requires-Dist: setuptools (<81)
Requires-Dist: shap (>=0.48.0,<0.49.0)
Requires-Dist: tensorflow (>=2.14.0,<2.15.0)
Requires-Dist: typing-extensions (>=4.11,<5)
Requires-Dist: xgboost (>=2.0.3,<2.1.0)
